{
  "entities": {
    "Q53832755": {
      "pageid": 54289488,
      "ns": 0,
      "title": "Q53832755",
      "lastrevid": 684169834,
      "modified": "2018-05-24T00:06:24Z",
      "type": "item",
      "id": "Q53832755",
      "labels": {
        "en": {
          "language": "en",
          "value": "Noah Kahan"
        }
      },
      "descriptions": {
        "en": {
          "language": "en",
          "value": "American singer-songwriter"
        }
      },
      "aliases": {},
      "claims": {
        "P434": [
          {
            "mainsnak": {
              "snaktype": "value",
              "property": "P434",
              "hash": "fbc646bb088c3d2fc52c05b35ebdd7f99a227c62",
              "datavalue": {
                "value": "a2a3f910-b188-43e7-81d0-f1ac2a2f3e12",
                "type": "string"
              },
              "datatype": "external-id"
            },
            "type": "statement",
            "id": "Q53832755$bb2f2991-4f09-feac-9e8d-71280e4ce483",
            "rank": "normal"
          }
        ],
        "P1728": [
          {
            "mainsnak": {
              "snaktype": "value",
              "property": "P1728",
              "hash": "4a9a8773dc4063715d5633cfce5952cf6b276984",
              "datavalue": {
                "value": "mn0003592649",
                "type": "string"
              },
              "datatype": "external-id"
            },
            "type": "statement",
            "id": "Q53832755$97dd8bf7-410c-879d-731d-0113733bbe1e",
            "rank": "normal"
          }
        ],
        "P1953": [
          {
            "mainsnak": {
              "snaktype": "value",
              "property": "P1953",
              "hash": "4d3dfecc4fc9097ee7f11a98a9238037a15236f3",
              "datavalue": {
                "value": "5951449",
                "type": "string"
              },
              "datatype": "external-id"
            },
            "type": "statement",
            "id": "Q53832755$8271f575-4fec-0855-da5f-5b48917a3c23",
            "rank": "normal"
          }
        ],
        "P2013": [
          {
            "mainsnak": {
              "snaktype": "value",
              "property": "P2013",
              "hash": "384a4e4e2187a81c1863aa748b845306cac31949",
              "datavalue": {
                "value": "noahkahanmusic",
                "type": "string"
              },
              "datatype": "external-id"
            },
            "type": "statement",
            "id": "Q53832755$ac67949b-4a24-0dd7-9062-e01f8ec167ca",
            "rank": "normal"
          }
        ],
        "P2002": [
          {
            "mainsnak": {
              "snaktype": "value",
              "property": "P2002",
              "hash": "e941a7ca42820a208a938dfaaf5258359da69a68",
              "datavalue": {
                "value": "noahkahan",
                "type": "string"
              },
              "datatype": "external-id"
            },
            "type": "statement",
            "id": "Q53832755$84003c4d-460b-4550-4592-6fddf5ac6809",
            "rank": "normal"
          }
        ],
        "P3040": [
          {
            "mainsnak": {
              "snaktype": "value",
              "property": "P3040",
              "hash": "d385b76679376eac5d09541ddb2a54590cefbc41",
              "datavalue": {
                "value": "noahkahan",
                "type": "string"
              },
              "datatype": "external-id"
            },
            "type": "statement",
            "id": "Q53832755$aea5456e-4dbe-d5c7-2e40-33bc73cebdbb",
            "rank": "normal"
          }
        ],
        "P2003": [
          {
            "mainsnak": {
              "snaktype": "value",
              "property": "P2003",
              "hash": "d635aa0a815f6b8a40287fc29150529ccf1281d3",
              "datavalue": {
                "value": "noahkahanmusic",
                "type": "string"
              },
              "datatype": "external-id"
            },
            "type": "statement",
            "id": "Q53832755$c2bb1a5a-4847-a0df-cae7-549632f4e477",
            "rank": "normal"
          }
        ],
        "P2850": [
          {
            "mainsnak": {
              "snaktype": "value",
              "property": "P2850",
              "hash": "54a5cf5682e14ddfd7b38a9153aabac7544f380c",
              "datavalue": {
                "value": "328583953",
                "type": "string"
              },
              "datatype": "external-id"
            },
            "type": "statement",
            "id": "Q53832755$27b6ecbd-45f3-cdf1-2aaa-27116e1c65bb",
            "rank": "normal"
          }
        ],
        "P31": [
          {
            "mainsnak": {
              "snaktype": "value",
              "property": "P31",
              "hash": "ad7d38a03cdd40cdc373de0dc4e7b7fcbccb31d9",
              "datavalue": {
                "value": {
                  "entity-type": "item",
                  "numeric-id": 5,
                  "id": "Q5"
                },
                "type": "wikibase-entityid"
              },
              "datatype": "wikibase-item"
            },
            "type": "statement",
            "id": "Q53832755$E7DC73EC-15A1-45DA-9938-63F29B9B57F3",
            "rank": "normal"
          }
        ]
      },
      "sitelinks": {
        "enwiki": {
          "site": "enwiki",
          "title": "Noah Kahan",
          "badges": [],
          "url": "https://en.wikipedia.org/wiki/Noah_Kahan"
        }
      }
    }
  }
}